{"nodes": [{"id": "phase2.uatPassed", "label": "Phase 2 UAT passed for rates screen", "file_type": "document", "source_file": ".planning\\phases\\02-exchange-rate-layer\\02-UAT.md", "source_location": "Tests and Summary", "source_url": null, "captured_at": "2026-07-04T00:00:00+08:00", "author": null, "contributor": null}], "edges": [{"source": "phase2.uatPassed", "target": "phase2.ratesScreenSummary", "relation": "passes_runtime_rates_screen_acceptance", "confidence": "EXTRACTED", "confidence_score": 1.0, "source_file": ".planning\\phases\\02-exchange-rate-layer\\02-UAT.md", "source_location": "Tests 1-5", "weight": 1.0}], "hyperedges": []}