{"nodes": [{"id": "space_reserved_fx_period_columns", "label": "Reserved space FX snapshot and period columns", "file_type": "document", "source_file": ".planning\\phases\\01-foundations-schema-reference-data\\01-01-PLAN.md", "source_location": "artifacts_this_phase_produces", "source_url": null, "captured_at": "2026-07-04T00:00:00+08:00", "author": null, "contributor": null}], "edges": [{"source": "phase01_foundations_schema_reference_data", "target": "space_reserved_fx_period_columns", "relation": "locks_schema_columns", "confidence": "EXTRACTED", "confidence_score": 1.0, "source_file": ".planning\\phases\\01-foundations-schema-reference-data\\01-01-PLAN.md", "source_location": "objective", "weight": 1.0}], "hyperedges": []}